crirm/__init__.py
crirm/criteria.py
crirm/main.py
crirm/util.py
crirm-0.3.dist-info/DESCRIPTION.rst
crirm-0.3.dist-info/METADATA
crirm-0.3.dist-info/RECORD
crirm-0.3.dist-info/WHEEL
crirm-0.3.dist-info/entry_points.txt
crirm-0.3.dist-info/metadata.json
crirm-0.3.dist-info/top_level.txt
