Metadata-Version: 2.0
Name: crirm
Version: 0.3
Summary: CRIteria REMove. Delete files based on various criteria like age, file size etc.
Home-page: http://github.com/lycis/crirm
Author: Daniel Eder
Author-email: daniel@deder.at
License: MIT
Download-URL: http://github.com/lycis/crirm
Platform: UNKNOWN
